pz_rail_bpz-1.2.4.dist-info/licenses/LICENSE
rail/bpz/__init__.py
rail/bpz/_version.py
rail/bpz/utils.py
rail/estimation/algos/bpz_lite.py
pz_rail_bpz-1.2.4.dist-info/METADATA
pz_rail_bpz-1.2.4.dist-info/WHEEL
pz_rail_bpz-1.2.4.dist-info/top_level.txt
pz_rail_bpz-1.2.4.dist-info/RECORD
